Metadata-Version: 2.1
Name: NERX
Version: 0.1.5
Summary: Named Entity Recognition
Home-page: https://gitee.com/summry/NERX
Author: summy
Author-email: fkfkfk2024@2925.com
License: UNKNOWN
Keywords: Pytorch,AI,Machine learning,Deep learning,torch,NER,Named Entity Recognition
Platform: UNKNOWN
Requires-Python: >=3.6
